[{"day":"2018-10-08","open":"13.890","high":"13.890","low":"13.410","close":"13.560","volume":"396480"},{"day":"2018-10-09","open":"13.550","high":"13.760","low":"13.440","close":"13.600","volume":"182840"},{"day":"2018-10-10","open":"13.490","high":"13.710","low":"13.490","close":"13.640","volume":"513220"},{"day":"2018-10-11","open":"13.480","high":"13.480","low":"12.730","close":"13.470","volume":"1205760"},{"day":"2018-10-12","open":"13.150","high":"13.440","low":"12.710","close":"13.440","volume":"1211040"},{"day":"2018-10-15","open":"13.220","high":"13.460","low":"13.000","close":"13.350","volume":"502540"},{"day":"2018-10-16","open":"13.430","high":"14.100","low":"13.350","close":"13.920","volume":"806272"},{"day":"2018-10-17","open":"13.920","high":"14.250","low":"13.640","close":"13.900","volume":"919032"},{"day":"2018-10-18","open":"13.900","high":"13.900","low":"12.660","close":"13.780","volume":"1230846"},{"day":"2018-10-19","open":"13.020","high":"13.800","low":"13.000","close":"13.800","volume":"1078368"}]