[{"day":"2004-04-15","open":"2.960","high":"3.040","low":"2.880","close":"3.000","volume":"2167133"},{"day":"2004-04-16","open":"2.980","high":"3.100","low":"2.920","close":"3.050","volume":"1167379"},{"day":"2004-04-19","open":"3.050","high":"3.070","low":"2.920","close":"2.950","volume":"927480"},{"day":"2004-04-20","open":"2.900","high":"3.000","low":"2.800","close":"2.810","volume":"1790034"},{"day":"2004-04-21","open":"2.750","high":"2.800","low":"2.670","close":"2.670","volume":"2256416"},{"day":"2004-04-22","open":"2.650","high":"2.800","low":"2.570","close":"2.800","volume":"2468280"},{"day":"2004-04-23","open":"2.850","high":"2.900","low":"2.720","close":"2.780","volume":"1357790"},{"day":"2004-04-26","open":"2.780","high":"2.920","low":"2.780","close":"2.920","volume":"1405634"},{"day":"2004-04-27","open":"2.950","high":"3.070","low":"2.900","close":"2.950","volume":"2858981"},{"day":"2004-04-28","open":"2.920","high":"3.000","low":"2.800","close":"2.870","volume":"2632841"}]