[{"day":"2018-10-08","open":"10.990","high":"11.040","low":"10.590","close":"10.810","volume":"406243"},{"day":"2018-10-09","open":"10.700","high":"10.930","low":"10.680","close":"10.890","volume":"173680"},{"day":"2018-10-10","open":"10.890","high":"11.040","low":"10.880","close":"10.890","volume":"82233"},{"day":"2018-10-11","open":"10.710","high":"10.710","low":"9.800","close":"9.910","volume":"591100"},{"day":"2018-10-12","open":"10.110","high":"10.360","low":"9.680","close":"10.250","volume":"437917"},{"day":"2018-10-15","open":"10.280","high":"10.590","low":"9.950","close":"10.090","volume":"277732"},{"day":"2018-10-16","open":"10.140","high":"10.360","low":"9.800","close":"9.990","volume":"136628"},{"day":"2018-10-17","open":"10.260","high":"10.260","low":"9.830","close":"9.910","volume":"178790"},{"day":"2018-10-18","open":"10.020","high":"10.020","low":"9.060","close":"9.720","volume":"185997"},{"day":"2018-10-19","open":"9.700","high":"10.000","low":"9.440","close":"9.870","volume":"159886"}]