[{"day":"2018-10-08","open":"4.920","high":"4.920","low":"4.820","close":"4.840","volume":"2839800"},{"day":"2018-10-09","open":"4.810","high":"4.920","low":"4.810","close":"4.890","volume":"1596130"},{"day":"2018-10-10","open":"4.880","high":"4.910","low":"4.830","close":"4.880","volume":"1718265"},{"day":"2018-10-11","open":"4.790","high":"4.820","low":"4.450","close":"4.540","volume":"4846316"},{"day":"2018-10-12","open":"4.500","high":"4.600","low":"4.350","close":"4.550","volume":"2349903"},{"day":"2018-10-15","open":"4.550","high":"4.600","low":"4.490","close":"4.500","volume":"1448787"},{"day":"2018-10-16","open":"4.490","high":"4.590","low":"4.370","close":"4.390","volume":"1879700"},{"day":"2018-10-17","open":"4.450","high":"4.480","low":"4.370","close":"4.430","volume":"1618800"},{"day":"2018-10-18","open":"4.430","high":"4.430","low":"4.300","close":"4.340","volume":"1915155"},{"day":"2018-10-19","open":"4.290","high":"4.400","low":"4.210","close":"4.390","volume":"2021760"}]