[{"day":"2018-10-08","open":"9.290","high":"10.150","low":"9.260","close":"9.930","volume":"4745418"},{"day":"2018-10-09","open":"9.910","high":"9.910","low":"9.510","close":"9.580","volume":"3464422"},{"day":"2018-10-10","open":"9.590","high":"9.590","low":"9.450","close":"9.450","volume":"1263555"},{"day":"2018-10-11","open":"9.290","high":"9.290","low":"8.510","close":"8.650","volume":"2152591"},{"day":"2018-10-12","open":"8.510","high":"8.750","low":"8.320","close":"8.630","volume":"1347626"},{"day":"2018-10-15","open":"8.620","high":"8.710","low":"8.150","close":"8.190","volume":"1504149"},{"day":"2018-10-16","open":"8.200","high":"8.370","low":"8.200","close":"8.320","volume":"894732"},{"day":"2018-10-17","open":"8.330","high":"8.490","low":"8.230","close":"8.470","volume":"728906"},{"day":"2018-10-18","open":"8.380","high":"8.420","low":"8.210","close":"8.220","volume":"700373"},{"day":"2018-10-19","open":"8.300","high":"8.460","low":"8.090","close":"8.400","volume":"750660"}]