[{"day":"2018-10-08","open":"50.220","high":"50.220","low":"47.690","close":"48.310","volume":"3033276"},{"day":"2018-10-09","open":"48.360","high":"48.870","low":"47.310","close":"47.860","volume":"2217899"},{"day":"2018-10-10","open":"48.050","high":"48.080","low":"44.890","close":"45.100","volume":"7318283"},{"day":"2018-10-11","open":"43.300","high":"45.180","low":"41.800","close":"44.500","volume":"5740815"},{"day":"2018-10-12","open":"44.000","high":"45.100","low":"42.400","close":"44.800","volume":"6569957"},{"day":"2018-10-15","open":"44.700","high":"44.700","low":"43.010","close":"43.160","volume":"3073141"},{"day":"2018-10-16","open":"43.160","high":"44.190","low":"42.510","close":"43.390","volume":"2402887"},{"day":"2018-10-17","open":"43.890","high":"43.980","low":"40.570","close":"42.970","volume":"3231005"},{"day":"2018-10-18","open":"42.420","high":"43.140","low":"41.180","close":"41.960","volume":"2260309"},{"day":"2018-10-19","open":"41.460","high":"44.910","low":"41.000","close":"44.820","volume":"3849262"}]