[{"day":"2018-10-08","open":"2.680","high":"2.680","low":"2.640","close":"2.640","volume":"1918329"},{"day":"2018-10-09","open":"2.630","high":"2.670","low":"2.620","close":"2.630","volume":"2006900"},{"day":"2018-10-10","open":"2.630","high":"2.650","low":"2.610","close":"2.620","volume":"1685500"},{"day":"2018-10-11","open":"2.600","high":"2.600","low":"2.360","close":"2.360","volume":"5184100"},{"day":"2018-10-12","open":"2.320","high":"2.400","low":"2.250","close":"2.360","volume":"3164400"},{"day":"2018-10-15","open":"2.380","high":"2.410","low":"2.370","close":"2.400","volume":"2851864"},{"day":"2018-10-16","open":"2.410","high":"2.430","low":"2.370","close":"2.380","volume":"1744900"},{"day":"2018-10-17","open":"2.400","high":"2.410","low":"2.380","close":"2.400","volume":"879224"},{"day":"2018-10-18","open":"2.400","high":"2.400","low":"2.280","close":"2.280","volume":"1671500"},{"day":"2018-10-19","open":"2.290","high":"2.310","low":"2.210","close":"2.300","volume":"2139521"}]