[{"day":"2018-10-08","open":"3.800","high":"3.890","low":"3.720","close":"3.740","volume":"4092643"},{"day":"2018-10-09","open":"3.710","high":"3.740","low":"3.660","close":"3.700","volume":"1965962"},{"day":"2018-10-10","open":"3.680","high":"3.730","low":"3.630","close":"3.690","volume":"2005200"},{"day":"2018-10-11","open":"3.650","high":"3.650","low":"3.320","close":"3.350","volume":"3713100"},{"day":"2018-10-12","open":"3.350","high":"3.360","low":"3.200","close":"3.290","volume":"2871343"},{"day":"2018-10-15","open":"3.260","high":"3.350","low":"3.190","close":"3.220","volume":"1909519"},{"day":"2018-10-16","open":"3.230","high":"3.250","low":"3.130","close":"3.160","volume":"1633200"},{"day":"2018-10-17","open":"3.180","high":"3.360","low":"3.130","close":"3.230","volume":"1773000"},{"day":"2018-10-18","open":"3.210","high":"3.210","low":"3.100","close":"3.140","volume":"1696605"},{"day":"2018-10-19","open":"3.100","high":"3.230","low":"3.060","close":"3.210","volume":"1925762"}]