[{"day":"2018-10-08","open":"5.830","high":"5.890","low":"5.740","close":"5.750","volume":"3309387"},{"day":"2018-10-09","open":"5.750","high":"5.800","low":"5.700","close":"5.740","volume":"1782079"},{"day":"2018-10-10","open":"5.720","high":"5.780","low":"5.720","close":"5.750","volume":"1195100"},{"day":"2018-10-11","open":"5.640","high":"5.640","low":"5.180","close":"5.220","volume":"6145558"},{"day":"2018-10-12","open":"5.200","high":"5.230","low":"5.030","close":"5.170","volume":"3257432"},{"day":"2018-10-15","open":"5.190","high":"5.200","low":"5.050","close":"5.070","volume":"2206064"},{"day":"2018-10-16","open":"5.070","high":"5.210","low":"5.070","close":"5.120","volume":"1842323"},{"day":"2018-10-17","open":"5.160","high":"5.200","low":"5.070","close":"5.160","volume":"1141200"},{"day":"2018-10-18","open":"5.150","high":"5.150","low":"4.980","close":"5.030","volume":"1548252"},{"day":"2018-10-19","open":"4.950","high":"5.110","low":"4.900","close":"5.100","volume":"2706062"}]