[{"day":"2018-10-08","open":"2.540","high":"2.570","low":"2.510","close":"2.520","volume":"2515800"},{"day":"2018-10-09","open":"2.550","high":"2.550","low":"2.520","close":"2.520","volume":"2689101"},{"day":"2018-10-10","open":"2.510","high":"2.530","low":"2.510","close":"2.520","volume":"1653300"},{"day":"2018-10-11","open":"2.450","high":"2.450","low":"2.270","close":"2.270","volume":"7417000"},{"day":"2018-10-12","open":"2.260","high":"2.310","low":"2.070","close":"2.280","volume":"4952450"},{"day":"2018-10-15","open":"2.280","high":"2.280","low":"2.180","close":"2.190","volume":"2515445"},{"day":"2018-10-16","open":"2.190","high":"2.200","low":"2.070","close":"2.120","volume":"5101192"},{"day":"2018-10-17","open":"2.130","high":"2.160","low":"2.100","close":"2.130","volume":"2236701"},{"day":"2018-10-18","open":"2.120","high":"2.120","low":"2.070","close":"2.120","volume":"3551432"},{"day":"2018-10-19","open":"2.090","high":"2.250","low":"2.030","close":"2.180","volume":"7224761"}]