[{"day":"2018-10-08","open":"6.260","high":"6.260","low":"6.070","close":"6.120","volume":"1249300"},{"day":"2018-10-09","open":"6.080","high":"6.160","low":"6.080","close":"6.120","volume":"707350"},{"day":"2018-10-10","open":"6.100","high":"6.150","low":"6.090","close":"6.120","volume":"663334"},{"day":"2018-10-11","open":"6.000","high":"6.020","low":"5.510","close":"5.520","volume":"3332250"},{"day":"2018-10-12","open":"5.530","high":"5.600","low":"5.130","close":"5.360","volume":"1901493"},{"day":"2018-10-15","open":"5.360","high":"5.460","low":"5.310","close":"5.310","volume":"1347850"},{"day":"2018-10-16","open":"5.310","high":"5.410","low":"5.030","close":"5.100","volume":"873000"},{"day":"2018-10-17","open":"5.250","high":"5.250","low":"5.080","close":"5.160","volume":"1068000"},{"day":"2018-10-18","open":"5.150","high":"5.150","low":"5.040","close":"5.060","volume":"1385234"},{"day":"2018-10-19","open":"5.000","high":"5.180","low":"4.950","close":"5.150","volume":"1485937"}]