[{"day":"2018-10-08","open":"10.710","high":"11.340","low":"10.550","close":"11.340","volume":"6703997"},{"day":"2018-10-09","open":"11.660","high":"11.910","low":"11.410","close":"11.910","volume":"12048941"},{"day":"2018-10-10","open":"11.880","high":"12.510","low":"11.830","close":"12.510","volume":"12846621"},{"day":"2018-10-11","open":"12.460","high":"12.980","low":"12.140","close":"12.480","volume":"15797995"},{"day":"2018-10-12","open":"12.540","high":"12.830","low":"11.900","close":"12.060","volume":"10001330"},{"day":"2018-10-15","open":"11.580","high":"12.140","low":"11.580","close":"11.600","volume":"6394612"},{"day":"2018-10-16","open":"11.760","high":"11.900","low":"11.020","close":"11.150","volume":"9923011"},{"day":"2018-10-17","open":"11.430","high":"11.440","low":"10.960","close":"11.270","volume":"4998934"},{"day":"2018-10-18","open":"11.230","high":"11.830","low":"11.050","close":"11.830","volume":"6249262"},{"day":"2018-10-19","open":"12.070","high":"12.410","low":"11.800","close":"12.150","volume":"9314130"}]