[{"day":"2007-04-16","open":"3.650","high":"3.650","low":"3.650","close":"3.650","volume":"1635518"},{"day":"2007-04-17","open":"3.830","high":"3.830","low":"3.830","close":"3.830","volume":"2330991"},{"day":"2007-04-18","open":"4.020","high":"4.020","low":"4.020","close":"4.020","volume":"1642940"},{"day":"2007-04-19","open":"4.220","high":"4.220","low":"4.110","close":"4.220","volume":"38207844"},{"day":"2007-04-20","open":"4.420","high":"4.430","low":"4.220","close":"4.430","volume":"23367115"},{"day":"2007-04-23","open":"4.630","high":"4.630","low":"4.210","close":"4.210","volume":"42098394"},{"day":"2007-04-24","open":"4.010","high":"4.290","low":"4.000","close":"4.050","volume":"27433407"},{"day":"2007-04-25","open":"4.010","high":"4.250","low":"3.850","close":"4.250","volume":"26942914"},{"day":"2007-04-26","open":"4.400","high":"4.460","low":"4.280","close":"4.460","volume":"19677491"},{"day":"2007-04-27","open":"4.680","high":"4.680","low":"4.580","close":"4.680","volume":"27755526"}]