[{"day":"2018-10-08","open":"5.860","high":"5.940","low":"5.740","close":"5.750","volume":"5517832"},{"day":"2018-10-09","open":"5.700","high":"5.820","low":"5.650","close":"5.670","volume":"3410903"},{"day":"2018-10-10","open":"5.680","high":"5.730","low":"5.610","close":"5.680","volume":"2584300"},{"day":"2018-10-11","open":"5.530","high":"5.530","low":"5.110","close":"5.120","volume":"6761403"},{"day":"2018-10-12","open":"5.110","high":"5.130","low":"4.660","close":"4.960","volume":"5751610"},{"day":"2018-10-15","open":"5.460","high":"5.460","low":"5.120","close":"5.120","volume":"14578008"},{"day":"2018-10-16","open":"5.000","high":"5.030","low":"4.710","close":"4.730","volume":"9205950"},{"day":"2018-10-17","open":"4.620","high":"4.840","low":"4.620","close":"4.790","volume":"5584297"},{"day":"2018-10-18","open":"4.790","high":"4.790","low":"4.400","close":"4.450","volume":"7062350"},{"day":"2018-10-19","open":"4.360","high":"4.900","low":"4.360","close":"4.710","volume":"9318342"}]