[{"day":"2018-10-08","open":"2.550","high":"2.560","low":"2.520","close":"2.520","volume":"2417134"},{"day":"2018-10-09","open":"2.540","high":"2.550","low":"2.520","close":"2.540","volume":"1998470"},{"day":"2018-10-10","open":"2.550","high":"2.580","low":"2.530","close":"2.570","volume":"1855060"},{"day":"2018-10-11","open":"2.530","high":"2.550","low":"2.410","close":"2.470","volume":"8980088"},{"day":"2018-10-12","open":"2.440","high":"2.540","low":"2.410","close":"2.470","volume":"5440870"},{"day":"2018-10-15","open":"2.480","high":"2.500","low":"2.450","close":"2.450","volume":"2194759"},{"day":"2018-10-16","open":"2.430","high":"2.480","low":"2.420","close":"2.450","volume":"3680914"},{"day":"2018-10-17","open":"2.480","high":"2.480","low":"2.440","close":"2.460","volume":"1082650"},{"day":"2018-10-18","open":"2.430","high":"2.450","low":"2.370","close":"2.400","volume":"2521300"},{"day":"2018-10-19","open":"2.310","high":"2.410","low":"2.310","close":"2.400","volume":"1998195"}]