[{"day":"2018-10-08","open":"8.210","high":"8.360","low":"8.180","close":"8.200","volume":"35672844"},{"day":"2018-10-09","open":"8.200","high":"8.330","low":"8.200","close":"8.290","volume":"24555650"},{"day":"2018-10-10","open":"8.310","high":"8.500","low":"8.280","close":"8.500","volume":"49060639"},{"day":"2018-10-11","open":"8.280","high":"8.310","low":"7.920","close":"7.990","volume":"61923309"},{"day":"2018-10-12","open":"7.930","high":"8.240","low":"7.850","close":"8.160","volume":"58713418"},{"day":"2018-10-15","open":"8.320","high":"8.470","low":"8.130","close":"8.200","volume":"82714293"},{"day":"2018-10-16","open":"8.160","high":"8.250","low":"7.760","close":"7.810","volume":"66458029"},{"day":"2018-10-17","open":"7.910","high":"7.980","low":"7.770","close":"7.950","volume":"63069353"},{"day":"2018-10-18","open":"7.850","high":"7.850","low":"7.350","close":"7.350","volume":"73800759"},{"day":"2018-10-19","open":"7.180","high":"7.560","low":"7.150","close":"7.440","volume":"80590237"}]