[{"day":"2018-10-08","open":"11.930","high":"12.050","low":"11.800","close":"11.800","volume":"405300"},{"day":"2018-10-09","open":"11.810","high":"11.980","low":"11.280","close":"11.400","volume":"688300"},{"day":"2018-10-10","open":"11.400","high":"11.490","low":"11.230","close":"11.350","volume":"449200"},{"day":"2018-10-11","open":"11.100","high":"11.100","low":"10.220","close":"10.220","volume":"1263601"},{"day":"2018-10-12","open":"10.100","high":"10.250","low":"9.570","close":"10.080","volume":"1959400"},{"day":"2018-10-15","open":"10.120","high":"10.150","low":"9.770","close":"9.770","volume":"615500"},{"day":"2018-10-16","open":"9.810","high":"10.050","low":"9.350","close":"9.610","volume":"468200"},{"day":"2018-10-17","open":"9.650","high":"9.800","low":"9.300","close":"9.550","volume":"944800"},{"day":"2018-10-18","open":"9.480","high":"9.650","low":"9.410","close":"9.530","volume":"1297100"},{"day":"2018-10-19","open":"9.650","high":"9.800","low":"9.280","close":"9.790","volume":"1849700"}]