[{"day":"2018-10-08","open":"17.000","high":"17.170","low":"16.090","close":"16.270","volume":"2684025"},{"day":"2018-10-09","open":"16.390","high":"16.600","low":"16.270","close":"16.370","volume":"1145940"},{"day":"2018-10-10","open":"16.380","high":"16.600","low":"16.350","close":"16.510","volume":"1190789"},{"day":"2018-10-11","open":"15.300","high":"15.800","low":"14.860","close":"14.860","volume":"3049920"},{"day":"2018-10-12","open":"14.550","high":"14.820","low":"13.630","close":"14.390","volume":"2899680"},{"day":"2018-10-15","open":"14.600","high":"15.030","low":"14.410","close":"14.480","volume":"1985900"},{"day":"2018-10-16","open":"14.480","high":"15.030","low":"14.370","close":"14.550","volume":"2246469"},{"day":"2018-10-17","open":"14.750","high":"15.130","low":"14.560","close":"15.080","volume":"3098080"},{"day":"2018-10-18","open":"14.960","high":"14.960","low":"14.110","close":"14.290","volume":"2554455"},{"day":"2018-10-19","open":"13.920","high":"15.720","low":"13.920","close":"15.170","volume":"3967620"}]