[{"day":"2018-10-08","open":"24.020","high":"24.450","low":"23.000","close":"23.000","volume":"1095500"},{"day":"2018-10-09","open":"23.000","high":"23.600","low":"23.000","close":"23.320","volume":"814032"},{"day":"2018-10-10","open":"23.390","high":"23.790","low":"23.250","close":"23.590","volume":"787052"},{"day":"2018-10-11","open":"22.770","high":"22.860","low":"21.230","close":"21.230","volume":"1623053"},{"day":"2018-10-12","open":"21.070","high":"21.330","low":"19.610","close":"20.840","volume":"1575238"},{"day":"2018-10-15","open":"22.300","high":"22.920","low":"21.930","close":"22.920","volume":"1488212"},{"day":"2018-10-16","open":"23.490","high":"24.490","low":"22.770","close":"22.800","volume":"4378236"},{"day":"2018-10-17","open":"23.020","high":"23.800","low":"22.880","close":"23.690","volume":"3121201"},{"day":"2018-10-18","open":"23.400","high":"23.430","low":"22.370","close":"22.370","volume":"2105544"},{"day":"2018-10-19","open":"21.490","high":"24.610","low":"21.330","close":"23.610","volume":"3198261"}]