[{"day":"2018-10-08","open":"9.900","high":"10.620","low":"9.110","close":"9.110","volume":"35447740"},{"day":"2018-10-09","open":"8.590","high":"9.600","low":"8.450","close":"9.150","volume":"31312620"},{"day":"2018-10-10","open":"8.990","high":"10.070","low":"8.580","close":"10.070","volume":"29501842"},{"day":"2018-10-11","open":"9.770","high":"10.550","low":"9.060","close":"9.160","volume":"33672852"},{"day":"2018-10-12","open":"8.380","high":"9.180","low":"8.380","close":"8.560","volume":"26284429"},{"day":"2018-10-15","open":"8.570","high":"9.000","low":"8.400","close":"8.650","volume":"23300428"},{"day":"2018-10-16","open":"8.450","high":"8.790","low":"8.300","close":"8.400","volume":"18433969"},{"day":"2018-10-17","open":"8.400","high":"8.460","low":"7.560","close":"7.590","volume":"25888325"},{"day":"2018-10-18","open":"7.350","high":"7.530","low":"6.980","close":"7.150","volume":"20853034"},{"day":"2018-10-19","open":"7.210","high":"7.450","low":"7.120","close":"7.250","volume":"18224268"}]