[{"day":"2018-10-08","open":"32.630","high":"35.660","low":"31.930","close":"33.800","volume":"2752583"},{"day":"2018-10-09","open":"33.590","high":"37.180","low":"33.590","close":"37.180","volume":"2467556"},{"day":"2018-10-10","open":"40.900","high":"40.900","low":"40.900","close":"40.900","volume":"569768"},{"day":"2018-10-11","open":"42.500","high":"44.930","low":"40.010","close":"40.700","volume":"9188929"},{"day":"2018-10-12","open":"36.930","high":"40.790","low":"36.630","close":"38.600","volume":"6488384"},{"day":"2018-10-15","open":"36.990","high":"38.000","low":"35.930","close":"37.900","volume":"4461997"},{"day":"2018-10-16","open":"37.000","high":"37.570","low":"34.110","close":"34.110","volume":"4805323"},{"day":"2018-10-17","open":"34.000","high":"34.430","low":"31.520","close":"32.920","volume":"3781702"},{"day":"2018-10-18","open":"32.110","high":"32.390","low":"29.800","close":"30.270","volume":"3139311"},{"day":"2018-10-19","open":"29.620","high":"31.020","low":"29.520","close":"30.800","volume":"2332302"}]