[{"day":"2018-10-08","open":"15.310","high":"15.750","low":"14.270","close":"14.270","volume":"3563229"},{"day":"2018-10-09","open":"14.270","high":"15.180","low":"14.270","close":"14.870","volume":"4295745"},{"day":"2018-10-10","open":"15.030","high":"15.170","low":"14.500","close":"14.810","volume":"3449121"},{"day":"2018-10-11","open":"14.000","high":"14.560","low":"13.330","close":"13.330","volume":"3854581"},{"day":"2018-10-12","open":"13.360","high":"13.730","low":"12.960","close":"13.420","volume":"3284456"},{"day":"2018-10-15","open":"13.480","high":"14.760","low":"13.480","close":"14.330","volume":"5009391"},{"day":"2018-10-16","open":"14.110","high":"14.590","low":"13.870","close":"14.220","volume":"5325197"},{"day":"2018-10-17","open":"14.350","high":"14.470","low":"13.510","close":"13.970","volume":"4153677"},{"day":"2018-10-18","open":"13.800","high":"14.380","low":"13.550","close":"13.810","volume":"3498081"},{"day":"2018-10-19","open":"13.130","high":"14.090","low":"13.000","close":"14.020","volume":"3333168"}]