[{"day":"2018-10-08","open":"21.800","high":"22.200","low":"21.200","close":"22.010","volume":"868000"},{"day":"2018-10-09","open":"22.100","high":"22.190","low":"21.700","close":"21.900","volume":"381669"},{"day":"2018-10-10","open":"21.880","high":"22.000","low":"21.580","close":"21.740","volume":"318547"},{"day":"2018-10-11","open":"21.200","high":"21.360","low":"19.570","close":"19.570","volume":"887889"},{"day":"2018-10-12","open":"19.350","high":"19.540","low":"18.350","close":"19.390","volume":"913359"},{"day":"2018-10-15","open":"19.380","high":"19.550","low":"19.010","close":"19.110","volume":"326196"},{"day":"2018-10-16","open":"18.990","high":"19.270","low":"18.500","close":"18.600","volume":"388600"},{"day":"2018-10-17","open":"18.960","high":"19.000","low":"17.700","close":"18.620","volume":"778600"},{"day":"2018-10-18","open":"18.250","high":"18.420","low":"17.820","close":"17.960","volume":"564200"},{"day":"2018-10-19","open":"17.960","high":"18.340","low":"17.630","close":"18.340","volume":"607599"}]