[{"day":"2018-10-08","open":"13.960","high":"13.970","low":"13.330","close":"13.480","volume":"8385726"},{"day":"2018-10-09","open":"13.300","high":"13.700","low":"13.300","close":"13.390","volume":"4762988"},{"day":"2018-10-10","open":"13.440","high":"13.560","low":"13.190","close":"13.330","volume":"4107228"},{"day":"2018-10-11","open":"12.950","high":"13.250","low":"12.410","close":"12.640","volume":"9286316"},{"day":"2018-10-12","open":"12.500","high":"13.900","low":"12.480","close":"13.900","volume":"12813789"},{"day":"2018-10-15","open":"14.010","high":"14.400","low":"13.760","close":"14.020","volume":"13510626"},{"day":"2018-10-16","open":"13.940","high":"14.150","low":"13.680","close":"13.960","volume":"7514605"},{"day":"2018-10-17","open":"14.190","high":"14.390","low":"13.700","close":"14.260","volume":"12284394"},{"day":"2018-10-18","open":"14.060","high":"14.190","low":"13.710","close":"13.730","volume":"8918627"},{"day":"2018-10-19","open":"13.590","high":"14.680","low":"13.330","close":"14.500","volume":"12389765"}]