[{"day":"2018-10-08","open":"13.080","high":"13.170","low":"12.800","close":"12.950","volume":"3043331"},{"day":"2018-10-09","open":"12.980","high":"13.120","low":"12.820","close":"13.090","volume":"2432241"},{"day":"2018-10-10","open":"13.210","high":"13.280","low":"12.920","close":"13.070","volume":"2527114"},{"day":"2018-10-11","open":"12.690","high":"12.690","low":"11.990","close":"12.270","volume":"5758793"},{"day":"2018-10-12","open":"12.270","high":"12.280","low":"11.500","close":"12.230","volume":"5477861"},{"day":"2018-10-15","open":"12.130","high":"12.450","low":"12.040","close":"12.190","volume":"3741741"},{"day":"2018-10-16","open":"12.290","high":"12.360","low":"12.000","close":"12.050","volume":"2652699"},{"day":"2018-10-17","open":"12.180","high":"12.580","low":"12.180","close":"12.530","volume":"4404385"},{"day":"2018-10-18","open":"12.500","high":"12.890","low":"12.420","close":"12.630","volume":"5590513"},{"day":"2018-10-19","open":"12.600","high":"13.140","low":"12.410","close":"13.010","volume":"4572181"}]