[{"day":"2018-10-08","open":"10.240","high":"10.240","low":"9.800","close":"9.840","volume":"1842600"},{"day":"2018-10-09","open":"9.890","high":"10.640","low":"9.860","close":"10.470","volume":"4569391"},{"day":"2018-10-10","open":"11.520","high":"11.520","low":"10.710","close":"10.950","volume":"7329294"},{"day":"2018-10-11","open":"10.440","high":"10.850","low":"10.150","close":"10.550","volume":"4964560"},{"day":"2018-10-12","open":"10.560","high":"10.740","low":"10.000","close":"10.670","volume":"4129931"},{"day":"2018-10-15","open":"10.700","high":"10.770","low":"10.110","close":"10.170","volume":"2986581"},{"day":"2018-10-16","open":"10.250","high":"10.400","low":"9.940","close":"10.070","volume":"2024154"},{"day":"2018-10-17","open":"10.270","high":"10.450","low":"9.950","close":"10.230","volume":"2525249"},{"day":"2018-10-18","open":"10.060","high":"10.190","low":"9.900","close":"10.000","volume":"2156782"},{"day":"2018-10-19","open":"9.780","high":"10.160","low":"9.660","close":"10.130","volume":"2627950"}]