[{"day":"2018-09-21","open":"6.830","high":"6.830","low":"6.680","close":"6.790","volume":"6059460"},{"day":"2018-09-25","open":"6.740","high":"6.790","low":"6.620","close":"6.790","volume":"5610172"},{"day":"2018-09-26","open":"6.760","high":"6.780","low":"6.640","close":"6.780","volume":"7747040"},{"day":"2018-09-27","open":"6.690","high":"6.780","low":"6.650","close":"6.780","volume":"9134420"},{"day":"2018-09-28","open":"6.760","high":"6.810","low":"6.700","close":"6.780","volume":"7283105"},{"day":"2018-10-08","open":"6.680","high":"6.750","low":"6.570","close":"6.700","volume":"6982660"},{"day":"2018-10-09","open":"6.660","high":"6.820","low":"6.030","close":"6.600","volume":"19747667"},{"day":"2018-10-10","open":"6.360","high":"6.500","low":"6.280","close":"6.330","volume":"9549262"},{"day":"2018-10-11","open":"6.190","high":"6.270","low":"5.860","close":"6.140","volume":"9764760"},{"day":"2018-10-12","open":"6.070","high":"6.080","low":"5.530","close":"5.530","volume":"13066422"}]